pyeventbus3/IO_performance_testing.py
pyeventbus3/Singleton.py
pyeventbus3/__init__.py
pyeventbus3/network_performance_testing.py
pyeventbus3/performance_testing.py
pyeventbus3/pyeventbus.py
pyeventbus3/pyeventbus3.py
pyeventbus3-0.10.dist-info/LICENSE
pyeventbus3-0.10.dist-info/METADATA
pyeventbus3-0.10.dist-info/WHEEL
pyeventbus3-0.10.dist-info/top_level.txt
pyeventbus3-0.10.dist-info/RECORD
