Metadata-Version: 1.1
Name: pyeventbus3
Version: 0.10
Summary: A Python EventBus
Home-page: https://github.com/FlavienVernier/pyeventbus
Author: Nanda Bhat, Flavien Vernier
Author-email: n89nanda@gmail.com, flavien.vernier@gmail.com
License: MIT
Keywords: python eventbus with threading and concurrency support
Platform: UNKNOWN
Classifier: Development Status :: 3 - Alpha
Classifier: License :: OSI Approved :: MIT License
Classifier: Programming Language :: Python :: 3
Classifier: Framework :: Flask
Classifier: Intended Audience :: Developers
Classifier: Intended Audience :: Science/Research
Classifier: Natural Language :: English
Classifier: Operating System :: OS Independent
